anml/__about__.py
anml/__init__.py
anml/data/__init__.py
anml/data/component.py
anml/data/example.py
anml/data/prototype.py
anml/data/validator.py
anml/getter/__init__.py
anml/getter/prior.py
anml/getter/spline.py
anml/parameter/__init__.py
anml/parameter/main.py
anml/parameter/smoothmapping.py
anml/prior/__init__.py
anml/prior/main.py
anml/prior/utils.py
anml/variable/__init__.py
anml/variable/main.py
anml/variable/spline.py
anml-0.2.1.dist-info/AUTHORS.rst
anml-0.2.1.dist-info/LICENSE
anml-0.2.1.dist-info/METADATA
anml-0.2.1.dist-info/WHEEL
anml-0.2.1.dist-info/top_level.txt
anml-0.2.1.dist-info/RECORD
