Metadata-Version: 2.1
Name: anml
Version: 0.2.1
Summary: ANML: A Nonlinear Modeling Library
Home-page: https://github.com/ihmeuw-msca/anml
Author: IHME Math Sciences
Author-email: ihme.math.sciences@gmail.com
License: BSD 2-Clause License
Platform: UNKNOWN
License-File: LICENSE
License-File: AUTHORS.rst
Requires-Dist: numpy (>=1.21)
Requires-Dist: pandas
Requires-Dist: scipy
Requires-Dist: xspline
Requires-Dist: click
Provides-Extra: dev
Requires-Dist: sphinx (>=3.0.0) ; extra == 'dev'
Requires-Dist: sphinx-autodoc-typehints ; extra == 'dev'
Requires-Dist: furo ; extra == 'dev'
Requires-Dist: sphinx-click ; extra == 'dev'
Requires-Dist: IPython ; extra == 'dev'
Requires-Dist: matplotlib ; extra == 'dev'
Requires-Dist: pytest ; extra == 'dev'
Requires-Dist: pytest-mock ; extra == 'dev'
Provides-Extra: docs
Requires-Dist: sphinx (>=3.0.0) ; extra == 'docs'
Requires-Dist: sphinx-autodoc-typehints ; extra == 'docs'
Requires-Dist: furo ; extra == 'docs'
Requires-Dist: sphinx-click ; extra == 'docs'
Requires-Dist: IPython ; extra == 'docs'
Requires-Dist: matplotlib ; extra == 'docs'
Provides-Extra: test
Requires-Dist: pytest ; extra == 'test'
Requires-Dist: pytest-mock ; extra == 'test'
